electrostatic/__init__.py
electrostatic/asgi.py
electrostatic/assets.py
electrostatic/typing.py
electrostatic/utils.py
electrostatic/wsgi.py
electrostatic-0.0.1.dist-info/LICENSE
electrostatic-0.0.1.dist-info/WHEEL
electrostatic-0.0.1.dist-info/METADATA
electrostatic-0.0.1.dist-info/RECORD
