Metadata-Version: 2.1
Name: electrostatic
Version: 0.0.1
Summary: Application or middleware to serve static files over ASGI or WSGI
Home-page: https://github.com/LucidDan/electrostatic
License: MIT
Keywords: asgi,staticfiles,web,server,wsgi
Author: Dan Sloan
Author-email: dan@lucidhorizons.com.au
Requires-Python: >=3.7,<4.0
Classifier: Development Status :: 2 - Pre-Alpha
Classifier: Intended Audience :: Developers
Classifier: License :: OSI Approved :: MIT License
Classifier: Natural Language :: English
Classifier: Programming Language :: Python :: 3
Classifier: Programming Language :: Python :: 3.10
Classifier: Programming Language :: Python :: 3.7
Classifier: Programming Language :: Python :: 3.8
Classifier: Programming Language :: Python :: 3.9
Provides-Extra: watchdog
Requires-Dist: asgiref (>=3.4.1,<4.0.0)
Requires-Dist: watchdog (>=2.1.6,<3.0.0); extra == "watchdog"
Project-URL: Repository, https://github.com/LucidDan/electrostatic
